odoo/addons/project_stage_closed/README.rst
odoo/addons/project_stage_closed/__init__.py
odoo/addons/project_stage_closed/__manifest__.py
odoo/addons/project_stage_closed/i18n/de.po
odoo/addons/project_stage_closed/i18n/es.po
odoo/addons/project_stage_closed/i18n/fi.po
odoo/addons/project_stage_closed/i18n/fr.po
odoo/addons/project_stage_closed/i18n/hr.po
odoo/addons/project_stage_closed/i18n/hu.po
odoo/addons/project_stage_closed/i18n/it.po
odoo/addons/project_stage_closed/i18n/lv.po
odoo/addons/project_stage_closed/i18n/nb.po
odoo/addons/project_stage_closed/i18n/nl.po
odoo/addons/project_stage_closed/i18n/nl_NL.po
odoo/addons/project_stage_closed/i18n/project_stage_closed.pot
odoo/addons/project_stage_closed/i18n/pt.po
odoo/addons/project_stage_closed/i18n/pt_BR.po
odoo/addons/project_stage_closed/i18n/pt_PT.po
odoo/addons/project_stage_closed/i18n/sl.po
odoo/addons/project_stage_closed/i18n/sv.po
odoo/addons/project_stage_closed/i18n/tr.po
odoo/addons/project_stage_closed/i18n/zh_CN.po
odoo/addons/project_stage_closed/models/__init__.py
odoo/addons/project_stage_closed/models/task_stage.py
odoo/addons/project_stage_closed/readme/CONTRIBUTORS.rst
odoo/addons/project_stage_closed/readme/DESCRIPTION.rst
odoo/addons/project_stage_closed/readme/USAGE.rst
odoo/addons/project_stage_closed/static/description/icon.png
odoo/addons/project_stage_closed/static/description/index.html
odoo/addons/project_stage_closed/views/task_stage.xml
odoo13_addon_project_stage_closed-13.0.1.0.1.dev6.dist-info/METADATA
odoo13_addon_project_stage_closed-13.0.1.0.1.dev6.dist-info/WHEEL
odoo13_addon_project_stage_closed-13.0.1.0.1.dev6.dist-info/top_level.txt
odoo13_addon_project_stage_closed-13.0.1.0.1.dev6.dist-info/RECORD
